Metadata-Version: 1.1
Name: rxray
Version: 1.0.0
Summary: RxPY operators to distribute computations with ray
Home-page: https://github.com/maki-nage/rxray.git
Author: Romain Picard
Author-email: romain.picard@oakbits.com
License: MIT
Platform: any
Classifier: Development Status :: 3 - Alpha
Classifier: License :: OSI Approved :: MIT License
Classifier: Intended Audience :: Developers
Classifier: Programming Language :: Python :: 3
Classifier: Topic :: System :: Distributed Computing
